Metadata-Version: 1.0
Name: sshEOS
Version: 1.0.8
Summary: python3 ssh module for Arista EOS
Home-page: https://github.com/FedericoOlivieri/networkAutomation/blob/master/python/modules/python3/sshEOS/sshEOS/__init__.py
Author: Federico Olivieri
Author-email: lvrfrc87@gmail.com
License: MIT
Platform: UNKNOWN
